LICENSE
MANIFEST.in
README.md
pyproject.toml
setup.cfg
setup.py
places/__init__.py
places/admin.py
places/apps.py
places/models.py
places/settings.py
places/tests.py
places/util.py
places/views.py
places/wagtail_hooks.py
places/migrations/0001_initial.py
places/migrations/0002_placespage_seo_description_template.py
places/migrations/0003_placespage_seo_priority_and_more.py
places/migrations/0004_place_updated_at_placespage_seo_change_frequency.py
places/migrations/__init__.py
places/migrations/__pycache__/0001_initial.cpython-311.pyc
places/migrations/__pycache__/0002_alter_place_address_alter_place_place_id_and_more.cpython-311.pyc
places/migrations/__pycache__/0002_placespage_seo_description_template.cpython-311.pyc
places/migrations/__pycache__/0003_placespage_seo_priority_and_more.cpython-311.pyc
places/migrations/__pycache__/0003_rename_place_name_place_name.cpython-311.pyc
places/migrations/__pycache__/0004_place_updated_at_placespage_seo_change_frequency.cpython-311.pyc
places/migrations/__pycache__/0004_placespage_sidebar_title.cpython-311.pyc
places/migrations/__pycache__/0005_place_slug.cpython-311.pyc
places/migrations/__pycache__/0006_alter_place_slug.cpython-311.pyc
places/migrations/__pycache__/0007_placespage_no_place_message.cpython-311.pyc
places/migrations/__pycache__/__init__.cpython-311.pyc
places/static/places/css/places.css
places/static/places/css/places.min.css
places/templates/places/places_detail.html
places/templates/places/places_page.html
wagtail_places.egg-info/PKG-INFO
wagtail_places.egg-info/SOURCES.txt
wagtail_places.egg-info/dependency_links.txt
wagtail_places.egg-info/requires.txt
wagtail_places.egg-info/top_level.txt